bailiwick/__init__.py
bailiwick/context.py
bailiwick/context_dict.py
bailiwick/errors.py
bailiwick-0.0.0.dev0.dist-info/LICENSE
bailiwick-0.0.0.dev0.dist-info/WHEEL
bailiwick-0.0.0.dev0.dist-info/METADATA
bailiwick-0.0.0.dev0.dist-info/RECORD
